crpt/__init__.py
crpt/loader.py
crpt-1.0.0.dist-info/METADATA
crpt-1.0.0.dist-info/WHEEL
crpt-1.0.0.dist-info/entry_points.txt
crpt-1.0.0.dist-info/top_level.txt
crpt-1.0.0.dist-info/RECORD
