Metadata-Version: 2.1
Name: crpt
Version: 1.0.0
Summary: A lightweight cryptography utilities package for Python developers.
Home-page: https://github.com/cryptoutils/crpt
Author: CryptoUtils
Author-email: support@cryptoutils.org
Keywords: crypto cryptography utils security encryption
Classifier: Development Status :: 4 - Beta
Classifier: Intended Audience :: Developers
Classifier: License :: OSI Approved :: MIT License
Classifier: Programming Language :: Python :: 3
Classifier: Topic :: Security :: Cryptography
Requires-Python: >=3.6
